learningmachine/__init__.py
learningmachine/base.py
learningmachine/classifier.py
learningmachine/regression.py
learningmachine/utils.py
learningmachine-2.7.0.dist-info/LICENSE
learningmachine-2.7.0.dist-info/METADATA
learningmachine-2.7.0.dist-info/WHEEL
learningmachine-2.7.0.dist-info/top_level.txt
learningmachine-2.7.0.dist-info/RECORD
