Metadata-Version: 2.1
Name: learningmachine
Version: 2.7.0
Summary: Machine Learning with uncertainty quantification and interpretability
Home-page: https://github.com/Techtonique/learningmachine_python
Author: T. Moudiki
Author-email: thierry.moudiki@gmail.com
License: BSD Clause Clear license
Keywords: learningmachine
Classifier: Development Status :: 2 - Pre-Alpha
Classifier: Intended Audience :: Developers
Classifier: License :: OSI Approved :: BSD License
Classifier: Natural Language :: English
Classifier: Programming Language :: Python :: 3
Classifier: Programming Language :: Python :: 3.6
Classifier: Programming Language :: Python :: 3.7
Classifier: Programming Language :: Python :: 3.8
Requires-Python: >=3.6
License-File: LICENSE
Requires-Dist: numpy
Requires-Dist: pandas
Requires-Dist: rpy2>=3.4.5
Requires-Dist: scikit-learn
Requires-Dist: scipy
